{
    "covid": [
        {
            "link": "https://megapolitan.kompas.com/read/2020/10/21/14591511/kasus-positif-di-tangsel-disebut-melonjak-karena-jumlah-tes-covid-19",
            "source": "Kompas",
            "title": "Kasus Positif di Tangsel Disebut Melonjak karena Jumlah Tes Covid-19 Meningkat"
        },
        {
            "link": "https://nasional.kompas.com/read/2020/10/21/14554101/wilayah-risiko-penularan-covid-19-bertambah-satgas-banyak-pemda-merasa-di",
            "source": "Kompas",
            "title": "Wilayah Risiko Penularan Covid-19 Bertambah Satgas Banyak Pemda Merasa di Zona Nyaman"
        },
        {
            "link": "https://megapolitan.kompas.com/read/2020/10/21/14490751/akan-jadi-kota-prioritas-depok-berencana-gelar-simulasi-vaksinasi-covid",
            "source": "Kompas",
            "title": "Akan Jadi Kota Prioritas Depok Berencana Gelar Simulasi Vaksinasi Covid-19"
        },
        {
            "link": "https://megapolitan.kompas.com/read/2020/10/21/14415241/meski-kasus-covid-19-di-tangsel-melonjak-kepatuhan-protokol-kesehatan",
            "source": "Kompas",
            "title": "Meski Kasus Covid-19 di Tangsel Melonjak Kepatuhan Protokol Kesehatan Diklaim Membaik"
        },
        {
            "link": "https://www.kompas.id/baca/video/2020/10/21/solidaritas-penyintas-covid-19/?utm_source=external_kompascom&utm_medium=berita_terkini&utm_campaign=kompascom",
            "source": "Kompas",
            "title": "Solidaritas Penyintas Covid-19"
        },
        {
            "link": "https://news.detik.com/berita-jawa-timur/d-5222536/kasus-aktif-positif-covid-19-di-jatim-sisa-2536-ini-data-persebarannya?tag_from=wp_nhl_15",
            "source": "Detik",
            "title": " Kasus Aktif Positif COVID-19 di Jatim Sisa 2536 Ini Data Persebarannya"
        },
        {
            "link": "https://news.detik.com/abc-australia/d-5222532/dorothy-perempuan-australia-berusia-107-tahun-yang-tak-khawatir-virus-corona?tag_from=wp_nhl_18",
            "source": "Detik",
            "title": " Dorothy Perempuan Australia Berusia 107 Tahun yang Tak Khawatir Virus Corona"
        }
    ],
    "general": [
        {
            "link": "https://properti.kompas.com/read/2020/10/21/144537321/tak-hanya-jalan-nama-jokowi-bakal-diabadikan-di-masjid-uea",
            "source": "Kompas",
            "title": "Tak Hanya Jalan Nama Jokowi Bakal Diabadikan di Masjid UEA"
        },
        {
            "link": "https://www.kompas.com/food/read/2020/10/21/145615275/resep-udang-dan-ikan-gratin-masakan-panggang-ala-perancis",
            "source": "Kompas",
            "title": "Resep Udang dan Ikan Gratin Masakan Panggang ala Perancis"
        },
        {
            "link": "https://www.kompas.com/hype/read/2020/10/21/145403766/kisah-kocak-di-balik-pemberian-nama-band-stinky",
            "source": "Kompas",
            "title": "Kisah Kocak di Balik Pemberian Nama Band Stinky"
        },
        {
            "link": "https://www.kompas.id/baca/internasional/2020/10/21/jokowi-terima-7-duta-besar-baru/?utm_source=external_kompascom&utm_medium=berita_terkini&utm_campaign=kompascom",
            "source": "Kompas",
            "title": "Jokowi Terima 7 Duta Besar Baru"
        },
        {
            "link": "https://nasional.kompas.com/read/2020/10/21/14534231/menko-pmk-minta-pemda-optimalkan-program-penanganan-stunting",
            "source": "Kompas",
            "title": "Menko PMK Minta Pemda Optimalkan Program Penanganan Stunting"
        },
        {
            "link": "https://regional.kompas.com/read/2020/10/21/14510561/seorang-pemuda-tewas-diduga-gantung-diri-tulis-pesan-di-buku-tabungan",
            "source": "Kompas",
            "title": "Seorang Pemuda Tewas Diduga Gantung Diri Tulis Pesan di Buku Tabungan"
        },
        {
            "link": "https://bola.kompas.com/read/2020/10/21/14504268/pele-legenda-sepak-bola-brasil-merasa-bersyukur",
            "source": "Kompas",
            "title": "Pele Legenda Sepak Bola Brasil Merasa Bersyukur"
        },
        {
            "link": "https://info.kompas.com/promo/epaper-kompasid?source=300x200",
            "source": "Kompas",
            "title": "Semakin Paham dengan ePaper Kompas GRATIS"
        },
        {
            "link": "https://regional.kompas.com/read/2020/10/21/14503231/2-dari-3-debat-kandidat-pilkada-makassar-bakal-berlangsung-di-jakarta",
            "source": "Kompas",
            "title": "2 dari 3 Debat Kandidat Pilkada Makassar Bakal Berlangsung di Jakarta"
        },
        {
            "link": "https://www.kompas.com/hype/read/2020/10/21/144929366/sinopsis-drama-korea-big-ketika-jiwa-gong-yoo-tertukar-tayang-di-viu",
            "source": "Kompas",
            "title": "Sinopsis Drama Korea Big Ketika Jiwa Gong Yoo Tertukar Tayang di VIU"
        },
        {
            "link": "https://travel.kompas.com/read/2020/10/21/144900127/korea-punya-tempat-kece-di-perumahan-warga-bisa-cafe-hopping",
            "source": "Kompas",
            "title": "Korea Punya Tempat Kece di Perumahan Warga Bisa Cafe Hopping"
        },
        {
            "link": "https://otomotif.kompas.com/read/2020/10/21/144723415/tiga-motor-ayam-jago-yang-sempat-populer-di-indonesia",
            "source": "Kompas",
            "title": "Tiga Motor Ayam Jago yang Sempat Populer di Indonesia"
        },
        {
            "link": "https://properti.kompas.com/read/2020/10/21/144537321/tak-hanya-jalan-nama-jokowi-bakal-diabadikan-di-masjid-uea",
            "source": "Kompas",
            "title": "Tak Hanya Jalan Nama Jokowi Bakal Diabadikan di Masjid UEA"
        },
        {
            "link": "https://www.kompas.id/baca/nusantara/2020/10/21/hadapi-la-nina-bmkg-ingatkan-petani-siapkan-irigasi/?utm_source=external_kompascom&utm_medium=berita_terkini&utm_campaign=kompascom",
            "source": "Kompas",
            "title": "Hadapi La Nina BMKG Ingatkan Petani Siapkan Irigasi"
        },
        {
            "link": "https://nasional.kompas.com/read/2020/10/21/14431721/temuan-tgpf-aparat-diduga-terlibat-dalam-kasus-penembakan-pendeta-yeremia",
            "source": "Kompas",
            "title": "Temuan TGPF Aparat Diduga Terlibat dalam Kasus Penembakan Pendeta Yeremia"
        },
        {
            "link": "https://nasional.kompas.com/read/2020/10/21/14410221/fredrich-yunadi-ajukan-pk-kpk-siap-hadapi",
            "source": "Kompas",
            "title": "Fredrich Yunadi Ajukan PK KPK Siap Hadapi"
        },
        {
            "link": "https://money.kompas.com/read/2020/10/21/144100926/keukeuh-minta-kenaikan-upah-kspi-bandingkan-dengan-zaman-habibie",
            "source": "Kompas",
            "title": "Keukeuh Minta Kenaikan Upah KSPI Bandingkan dengan Zaman Habibie"
        },
        {
            "link": "https://money.kompas.com/read/2020/10/21/143620326/dpr-kunjungan-pm-jepang-harus-bisa-dimanfaatkan-pengusaha-nasional",
            "source": "Kompas",
            "title": "DPR Kunjungan PM Jepang Harus Bisa Dimanfaatkan Pengusaha Nasional"
        },
        {
            "link": "https://edukasi.kompas.com/read/2020/10/21/143610771/ingin-belajar-jadi-pendidik-abk-ini-11-ptn-pilihannya",
            "source": "Kompas",
            "title": "Ingin Belajar Jadi Pendidik ABK Ini 11 PTN Pilihannya"
        },
        {
            "link": "https://finance.detik.com/foto-bisnis/d-5222548/melihat-limbah-kayu-jadi-furnitur-keren?tag_from=wp_nhl_2",
            "source": "Detik",
            "title": " Melihat Limbah Kayu Jadi Furnitur Keren"
        },
        {
            "link": "https://news.detik.com/detiktv/d-5222446/tgpf-intan-jaya--aparat-diduga-terlibat-pembunuhan-pendeta-yeremia?tag_from=wp_nhl_3",
            "source": "Detik",
            "title": " TGPF Intan Jaya Aparat Diduga Terlibat Pembunuhan Pendeta Yeremia"
        },
        {
            "link": "https://finance.detik.com/berita-ekonomi-bisnis/d-5222547/hati-hati-penipuan-begini-cara-cek-penerima-banpres-umkm-yang-benar?tag_from=wp_nhl_4",
            "source": "Detik",
            "title": " Hati-hati Penipuan Begini Cara Cek Penerima Banpres UMKM yang Benar"
        },
        {
            "link": "https://sport.detik.com/sepakbola/uefa/d-5222447/man-united-layak-menang-atas-psg-karena-hal-ini?tag_from=wp_nhl_6",
            "source": "Detik",
            "title": " Man United Layak Menang atas PSG karena Hal Ini"
        },
        {
            "link": "https://news.detik.com/berita/d-5222448/jadi-anak-buah-prabowo-2-eks-anggota-tim-mawar-naik-pangkat-jadi-mayjen?tag_from=wp_nhl_7",
            "source": "Detik",
            "title": " Jadi Anak Buah Prabowo 2 Eks Anggota Tim Mawar Naik Pangkat Jadi Mayjen"
        },
        {
            "link": "https://news.detik.com/foto-news/d-5222540/semangat-siswa-sd-belajar-daring-di-tengah-banjir-rob?tag_from=wp_nhl_8",
            "source": "Detik",
            "title": " Semangat Siswa SD Belajar Daring di Tengah Banjir Rob"
        },
        {
            "link": "https://news.detik.com/berita/d-5222539/seluruh-komisi-dprd-rapat-di-resort-puncak-milik-pemda-dki-800-orang-hadir?tag_from=wp_nhl_9",
            "source": "Detik",
            "title": " Seluruh Komisi DPRD Rapat di Resort Puncak Milik Pemda DKI 800 Orang Hadir"
        },
        {
            "link": "https://finance.detik.com/moneter/d-5222538/digeruduk-nasabah-bumiputera-mau-cicil-klaim-bulan-depan?tag_from=wp_nhl_10",
            "source": "Detik",
            "title": " Digeruduk Nasabah Bumiputera Mau Cicil Klaim Bulan Depan"
        },
        {
            "link": "https://hot.detik.com/kpop/d-5222388/sapa-army-di-v-live-siaran-jimin-bts-tembus-angka-9-juta-penonton?tag_from=wp_nhl_12",
            "source": "Detik",
            "title": " Sapa ARMY di V Live Siaran Jimin BTS Tembus Angka 9 Juta Penonton"
        },
        {
            "link": "https://news.detik.com/berita/d-5222537/peras-pengemis-disabilitas-3-oknum-satpol-pp-batam-jadi-tersangka?tag_from=wp_nhl_13",
            "source": "Detik",
            "title": " Peras Pengemis Disabilitas 3 Oknum Satpol PP Batam Jadi Tersangka"
        },
        {
            "link": "https://wolipop.detik.com/entertainment-news/d-5222458/viral-suara-berisik-misterius-dari-apartemen-yang-sudah-2-tahun-kosong?tag_from=wp_nhl_14",
            "source": "Detik",
            "title": " Viral Suara Berisik Misterius dari Apartemen yang Sudah 2 Tahun Kosong"
        },
        {
            "link": "https://news.detik.com/berita-jawa-barat/d-5222535/nyatakan-dukungan-pada-salahsatu-calon-kades-di-cianjur-terancam-pidana?tag_from=wp_nhl_16",
            "source": "Detik",
            "title": " Nyatakan Dukungan Pada Salahsatu Calon Kades di Cianjur Terancam Pidana"
        },
        {
            "link": "https://finance.detik.com/bursa-dan-valas/d-5222534/tok-darmawan-junaidi-resmi-jadi-dirut-bank-mandiri?tag_from=wp_nhl_17",
            "source": "Detik",
            "title": " Tok Darmawan Junaidi Resmi Jadi Dirut Bank Mandiri"
        },
        {
            "link": "https://news.detik.com/foto-news/d-5222526/duh-badan-jalan-di-pasar-senen-jadi-lokasi-parkir-liar?tag_from=wp_nhl_20",
            "source": "Detik",
            "title": " Duh Badan Jalan di Pasar Senen Jadi Lokasi Parkir Liar"
        },
        {
            "link": "https://oto.detik.com/berita/d-5222525/hasil-studi-emisi-mobil-hybrid-tidak-beda-dengan-mobil-bensin?tag_from=wp_nhl_21",
            "source": "Detik",
            "title": " Hasil Studi Emisi Mobil Hybrid Tidak Beda dengan Mobil Bensin"
        },
        {
            "link": "https://news.detik.com/berita/d-5222523/sopir-taksi-online-dikeroyok-di-polrestabes-palembang-saat-hendak-minta-tolong?tag_from=wp_nhl_22",
            "source": "Detik",
            "title": " Sopir Taksi Online Dikeroyok di Polrestabes Palembang Saat Hendak Minta Tolong"
        },
        {
            "link": "https://travel.detik.com/domestic-destination/d-5222521/asyiknya-wisata-dengan-mobil-offroad-di-sulsel?tag_from=wp_nhl_24",
            "source": "Detik",
            "title": " Asyiknya Wisata dengan Mobil Offroad di Sulsel"
        },
        {
            "link": "https://news.detik.com/abc-australia/d-5222518/warga-asal-meksiko-mendapat-diskriminasi-saat-hendak-sewa-rumah-di-australia?tag_from=wp_nhl_25",
            "source": "Detik",
            "title": " Warga Asal Meksiko Mendapat Diskriminasi Saat Hendak Sewa Rumah di Australia"
        },
        {
            "link": "https://news.detik.com/berita/d-5222488/buntut-siswa-smk-nikahi-2-abg-semua-desa-di-lombok-tolak-pernikahan-anak?tag_from=wp_nhl_26",
            "source": "Detik",
            "title": " Buntut Siswa SMK Nikahi 2 ABG Semua Desa di Lombok Tolak Pernikahan Anak"
        },
        {
            "link": "https://news.detik.com/berita-jawa-tengah/d-5222519/bpptkg-intensitas-kegempaan-gunung-merapi-meningkat?tag_from=wp_nhl_27",
            "source": "Detik",
            "title": " BPPTKG Intensitas Kegempaan Gunung Merapi Meningkat"
        },
        {
            "link": "https://health.detik.com/berita-detikhealth/d-5222517/5-warga-korsel-meninggal-usai-disuntik-vaksin-flu?tag_from=wp_nhl_28",
            "source": "Detik",
            "title": " 5 Warga Korsel Meninggal Usai Disuntik Vaksin Flu"
        },
        {
            "link": "https://inet.detik.com/consumer/d-5222465/samsung-galaxy-z-fold-2-harga-spesifikasi-dan-desain?tag_from=wp_nhl_29",
            "source": "Detik",
            "title": " Samsung Galaxy Z Fold 2 Harga Spesifikasi dan Desain"
        },
        {
            "link": "https://finance.detik.com/berita-ekonomi-bisnis/d-5222515/siap-siap-blt-subsidi-gaji-rp-600-ribu-tahap-ii-cair-november?tag_from=wp_nhl_30",
            "source": "Detik",
            "title": " Siap-siap BLT Subsidi Gaji Rp 600 Ribu Tahap II Cair November"
        },
        {
            "link": "https://www.cnbcindonesia.com/market/20201021143910-19-196026/akuisisi-adira-zurich-insurance-siap-jadi-asuransi-syariah",
            "source": "CNBC Indonesia",
            "title": "Akuisisi Adira Zurich Insurance Siap Jadi Asuransi Syariah"
        },
        {
            "link": "https://www.cnbcindonesia.com/news/20201021144301-4-196028/demo-mah-lewat-thailand-resmi-buka-pintu-turis-china",
            "source": "CNBC Indonesia",
            "title": "Demo Mah Lewat Thailand Resmi Buka Pintu Turis China "
        },
        {
            "link": "https://www.cnbcindonesia.com/tech/20201021143728-37-196024/dipakai-2022-ini-tahapan-pengembangan-vaksin-merah-putih",
            "source": "CNBC Indonesia",
            "title": "Dipakai 2022 Ini Tahapan Pengembangan Vaksin Merah Putih"
        },
        {
            "link": "https://www.cnbcindonesia.com/market/20201021143942-17-196025/bursa-eropa-merah-saat-pembukaan-tunggu-laporan-keuangan",
            "source": "CNBC Indonesia",
            "title": "Bursa Eropa Merah Saat Pembukaan Tunggu Laporan Keuangan"
        },
        {
            "link": "https://www.cnbcindonesia.com/news/20201021142129-4-196021/bos-buruh-kami-minta-upah-2021-naik-8-tapi-bisa-nego",
            "source": "CNBC Indonesia",
            "title": "Bos Buruh Kami Minta Upah 2021 Naik 8 Tapi Bisa Nego"
        },
        {
            "link": "https://www.cnbcindonesia.com/market/20201021115027-18-195973/tuntut-klaim-rp-53-t-nasabah-sandera-markas-bumiputera",
            "source": "CNBC Indonesia",
            "title": "Tuntut Klaim Rp 53 T Nasabah Sandera Markas Bumiputera"
        },
        {
            "link": "https://www.cnbcindonesia.com/lifestyle/20201021143401-33-196023/wow-beruang-ini-model-binatang-terlaris-dari-rusia",
            "source": "CNBC Indonesia",
            "title": "Wow Beruang Ini Model Binatang Terlaris dari Rusia"
        },
        {
            "link": "https://www.cnbcindonesia.com/market/20201021135559-17-196016/kurs-euro-melesat-4-hari-beruntun-awas-digoyang-ecb",
            "source": "CNBC Indonesia",
            "title": "Kurs Euro Melesat 4 Hari Beruntun Awas Digoyang ECB"
        },
        {
            "link": "https://www.cnbcindonesia.com/market/20201021142303-17-196022/beredar-susunan-direksi-mandiri-saat-rupslb-ini-bocorannya",
            "source": "CNBC Indonesia",
            "title": "Beredar Susunan Direksi Mandiri Saat RUPSLB Ini Bocorannya"
        },
        {
            "link": "https://www.cnbcindonesia.com/market/20201021135925-17-196018/ada-covid-produksi-nikel-vale-malah-melesat-104-hingga-q3",
            "source": "CNBC Indonesia",
            "title": "Ada Covid Produksi Nikel Vale Malah Melesat 104 Hingga Q3"
        },
        {
            "link": "https://www.cnbcindonesia.com/market/20201021135421-17-196015/10-tahun-perusahaan-yang-melantai-di-bursa-itu-itu-saja",
            "source": "CNBC Indonesia",
            "title": "10 Tahun Perusahaan yang Melantai di Bursa Itu-itu Saja"
        },
        {
            "link": "https://www.cnbcindonesia.com/news/20201021132316-4-196012/bioskop-dki-buka-hari-ini-hanya-usia-12-60-tahun-boleh-masuk",
            "source": "CNBC Indonesia",
            "title": "Bioskop DKI Buka Hari Ini Hanya Usia 12-60 Tahun Boleh Masuk"
        },
        {
            "link": "https://www.cnnindonesia.com/nasional/20201021143944-12-561061/pengadilan-tinggi-tambah-2-tahun-bui-bagi-aspri-eks-menpora",
            "source": "CNN Indonesia",
            "title": "Pengadilan Tinggi Tambah 2 Tahun Bui Bagi Aspri Eks Menpora"
        },
        {
            "link": "https://www.cnnindonesia.com/nasional/20201021131445-32-560997/mahfud-md-sentil-kepemimpinan-amien-rais-dan-gatot-nurmantyo",
            "source": "CNN Indonesia",
            "title": "Mahfud MD Sentil Kepemimpinan Amien Rais dan Gatot Nurmantyo"
        },
        {
            "link": "https://www.cnnindonesia.com/internasional/20201021121618-134-560962/pemenggal-guru-prancis-sempat-tukar-pesan-dengan-ayah-murid",
            "source": "CNN Indonesia",
            "title": "Pemenggal Guru Prancis Sempat Tukar Pesan dengan Ayah Murid"
        },
        {
            "link": "https://www.cnnindonesia.com/nasional/20201021142631-32-561049/7-catatan-merah-pks-untuk-setahun-jokowi-maruf",
            "source": "CNN Indonesia",
            "title": "7 Catatan Merah PKS untuk Setahun Jokowi-Maruf"
        },
        {
            "link": "https://www.cnnindonesia.com/gaya-hidup/20201021131415-269-560998/7-hotel-bergaya-rumah-pohon-untuk-staycation",
            "source": "CNN Indonesia",
            "title": "7 Hotel Bergaya Rumah Pohon untuk Staycation"
        },
        {
            "link": "https://www.cnnindonesia.com/ekonomi/20201021134800-92-561019/mckinsey-hanya-21-persen-perusahaan-ri-terapkan-industri-40",
            "source": "CNN Indonesia",
            "title": "McKinsey Hanya 21 Persen Perusahaan RI Terapkan Industri 40"
        },
        {
            "link": "https://www.cnnindonesia.com/nasional/20201021142500-12-561046/mahfud-minta-polri-dan-kejaksaan-selesaikan-kasus-intan-jaya",
            "source": "CNN Indonesia",
            "title": "Mahfud Minta Polri dan Kejaksaan Selesaikan Kasus Intan Jaya"
        },
        {
            "link": "https://www.cnnindonesia.com/olahraga/20201021132907-142-561005/bayern-vs-atletico-pembuktian-lewandowski-dan-suarez",
            "source": "CNN Indonesia",
            "title": "Bayern vs Atletico Pembuktian Lewandowski dan Suarez"
        },
        {
            "link": "https://www.cnnindonesia.com/hiburan/20201021065605-234-560804/model-manohara-prihatin-viral-puluhan-anjing-diduga-dijual",
            "source": "CNN Indonesia",
            "title": "Model Manohara Prihatin Viral Puluhan Anjing Diduga Dijual"
        },
        {
            "link": "https://www.cnnindonesia.com/nasional/20201021102359-24-560918/video-polri-bantah-video-viral-polisi-menyusup-massa-aksi",
            "source": "CNN Indonesia",
            "title": "VIDEO Polri Bantah Video Viral Polisi Menyusup Massa Aksi"
        },
        {
            "link": "https://www.cnnindonesia.com/tv/20201021144327-407-561060/video-rs-mengcovidkan-pasien-menkes-kita-punya-nurani",
            "source": "CNN Indonesia",
            "title": "VIDEO RS Mengcovidkan Pasien Menkes Kita Punya Nurani"
        },
        {
            "link": "https://www.cnnindonesia.com/tv/20201021141736-407-561040/video-maruf-amin-dorong-warga-untuk-wakaf-uang",
            "source": "CNN Indonesia",
            "title": "VIDEO Maruf Amin Dorong Warga Untuk Wakaf Uang"
        },
        {
            "link": "https://www.cnnindonesia.com/tv/20201021134124-405-561010/video-tes-pcr-kilat-hasil-keluar-5-jam",
            "source": "CNN Indonesia",
            "title": "VIDEO Tes PCR Kilat Hasil Keluar 5 Jam"
        },
        {
            "link": "https://www.cnnindonesia.com/ekonomi/20201021134807-92-561013/eks-menkeu-sby-tuding-bursa-kerja-jadi-penghalang-investasi",
            "source": "CNN Indonesia",
            "title": "Eks Menkeu SBY Tuding Bursa Kerja Jadi Penghalang Investasi"
        },
        {
            "link": "https://www.cnnindonesia.com/gaya-hidup/20201021131857-255-561000/5-manfaat-makan-ceker-ayam-untuk-kesehatan",
            "source": "CNN Indonesia",
            "title": "5 Manfaat Makan Ceker Ayam untuk Kesehatan"
        },
        {
            "link": "https://www.cnnindonesia.com/nasional/20201021131232-20-560991/20-titik-jalur-tengkorak-di-jadetabek-jaktim-depok-terbanyak",
            "source": "CNN Indonesia",
            "title": "20 Titik Jalur Tengkorak di Jadetabek Jaktim-Depok Terbanyak"
        },
        {
            "link": "https://www.cnnindonesia.com/teknologi/20201021122248-384-560967/identitas-bus-listrik-rp2-miliar-buatan-inka",
            "source": "CNN Indonesia",
            "title": "Identitas Bus Listrik Rp2 Miliar Buatan INKA"
        },
        {
            "link": "https://www.cnnindonesia.com/internasional/20201021134517-120-561020/pangeran-arab-saudi-nawaf-bin-saud-meninggal-dunia",
            "source": "CNN Indonesia",
            "title": "Pangeran Arab Saudi Nawaf bin Saud Meninggal Dunia"
        },
        {
            "link": "https://www.cnnindonesia.com/olahraga/20201021105632-142-560930/perpanjang-kontrak-pique-khianati-messi-di-barcelona",
            "source": "CNN Indonesia",
            "title": "Perpanjang Kontrak Pique Khianati Messi Di Barcelona"
        },
        {
            "link": "https://www.cnnindonesia.com/ekonomi/20201021134846-532-561015/sri-mulyani-siapkan-dana-pen-rp238-t-buat-pesantren-madrasah",
            "source": "CNN Indonesia",
            "title": "Sri Mulyani Siapkan Dana PEN Rp238 T Buat Pesantren-Madrasah"
        },
        {
            "link": "https://www.cnnindonesia.com/nasional/20201021134655-32-561016/kader-golkar-ingin-airlangga-hartarto-jadi-capres-2024",
            "source": "CNN Indonesia",
            "title": "Kader Golkar Ingin Airlangga Hartarto Jadi Capres 2024"
        },
        {
            "link": "https://www.cnnindonesia.com/hiburan/20201021121709-220-560958/xxi-tunda-buka-bioskop-di-jakarta-meski-kantongi-izin-pemprov",
            "source": "CNN Indonesia",
            "title": "XXI Tunda Buka Bioskop di Jakarta meski Kantongi Izin Pemprov"
        },
        {
            "link": "https://www.cnnindonesia.com/nasional/20201021134545-32-561012/pdip-setahun-jokowi-maruf-masih-ada-elite-politik-yang-iri",
            "source": "CNN Indonesia",
            "title": "PDIP Setahun Jokowi-Maruf Masih Ada Elite Politik yang Iri"
        },
        {
            "link": "https://www.cnnindonesia.com/ekonomi/20201021131609-532-560995/maruf-amin-ajak-masyarakat-himpun-pahala-lewat-wakaf",
            "source": "CNN Indonesia",
            "title": "Maruf Amin Ajak Masyarakat Himpun Pahala Lewat Wakaf"
        },
        {
            "link": "https://www.cnnindonesia.com/teknologi/20201021105441-199-560936/misi-pesawat-antariksa-nasa-kumpulkan-batu-di-asteroid-bennu",
            "source": "CNN Indonesia",
            "title": "Misi Pesawat Antariksa NASA Kumpulkan Batu di Asteroid Bennu"
        },
        {
            "link": "https://www.cnnindonesia.com/olahraga/20201021131736-178-560996/ufc-254-lebih-besar-dibanding-khabib-vs-mcgregor",
            "source": "CNN Indonesia",
            "title": "UFC 254 Lebih Besar Dibanding Khabib vs McGregor"
        },
        {
            "link": "https://www.cnnindonesia.com/gaya-hidup/20201021122614-269-560964/rute-penerbangan-terpanjang-di-dunia-kembali-beroperasi",
            "source": "CNN Indonesia",
            "title": "Rute Penerbangan Terpanjang di Dunia Kembali Beroperasi"
        },
        {
            "link": "https://www.cnnindonesia.com/ekonomi/20201021132342-532-561002/pendaftaran-kartu-prakerja-gelombang-11-dijadwalkan-bulan-ini",
            "source": "CNN Indonesia",
            "title": "Pendaftaran Kartu Prakerja Gelombang 11 Dijadwalkan Bulan Ini"
        },
        {
            "link": "https://www.cnnindonesia.com/nasional/20201021131904-12-561001/jaksa-minta-hakim-tolak-eksepsi-pinangki",
            "source": "CNN Indonesia",
            "title": "Jaksa Minta Hakim Tolak Eksepsi Pinangki"
        },
        {
            "link": "https://www.cnnindonesia.com/nasional/20201021101629-32-560919/tim-akhyar-laporkan-wagub-sumut-diduga-dukung-mantu-jokowi",
            "source": "CNN Indonesia",
            "title": "Tim Akhyar Laporkan Wagub Sumut Diduga Dukung Mantu Jokowi"
        },
        {
            "link": "https://www.cnnindonesia.com/nasional/20201021092346-12-560898/polri-bantah-video-viral-polisi-menyamar-massa-aksi-mahasiswa",
            "source": "CNN Indonesia",
            "title": "Polri Bantah Video Viral Polisi Menyamar Massa Aksi Mahasiswa"
        },
        {
            "link": "https://www.cnnindonesia.com/nasional/20201021090130-12-560872/kampanye-libatkan-asn-cawalkot-demokrat-jadi-tersangka",
            "source": "CNN Indonesia",
            "title": "Kampanye Libatkan ASN Cawalkot Demokrat Jadi Tersangka"
        },
        {
            "link": "https://www.cnnindonesia.com/ekonomi/20201021134846-532-561015/sri-mulyani-siapkan-dana-pen-rp238-t-buat-pesantren-madrasah",
            "source": "CNN Indonesia",
            "title": "Sri Mulyani Siapkan Dana PEN Rp238 T Buat Pesantren-Madrasah"
        },
        {
            "link": "https://www.cnnindonesia.com/nasional/20201021131445-32-560997/mahfud-md-sentil-kepemimpinan-amien-rais-dan-gatot-nurmantyo",
            "source": "CNN Indonesia",
            "title": "Mahfud MD Sentil Kepemimpinan Amien Rais dan Gatot Nurmantyo"
        },
        {
            "link": "https://www.cnnindonesia.com/nasional/20201021125131-12-560975/laporan-tgpf-intan-jaya-ada-dugaan-keterlibatan-oknum-aparat",
            "source": "CNN Indonesia",
            "title": "Laporan TGPF Intan Jaya Ada Dugaan Keterlibatan Oknum Aparat"
        },
        {
            "link": "https://www.cnnindonesia.com/nasional/20201021121445-12-560957/polri-perwira-intel-halangi-sabhara-pukul-mahasiswa-jambi",
            "source": "CNN Indonesia",
            "title": "Polri Perwira Intel Halangi Sabhara Pukul Mahasiswa Jambi"
        },
        {
            "link": "https://www.cnnindonesia.com/internasional/20201021134517-120-561020/pangeran-arab-saudi-nawaf-bin-saud-meninggal-dunia",
            "source": "CNN Indonesia",
            "title": "Pangeran Arab Saudi Nawaf bin Saud Meninggal Dunia"
        },
        {
            "link": "https://www.cnnindonesia.com/nasional/20201012081351-33-557206/tunda-pilkada-serentak-pak-presiden-yang-terhormat",
            "source": "CNN Indonesia",
            "title": "Tunda Pilkada Serentak Pak Presiden yang Terhormat"
        },
        {
            "link": "https://www.cnnindonesia.com/olahraga/20201012093413-179-557233/surat-untuk-mendiang-kobe",
            "source": "CNN Indonesia",
            "title": "Surat untuk Mendiang Kobe"
        },
        {
            "link": "https://www.cnnindonesia.com/nasional/20201006115735-33-554877/rezim-uu-omnibus-cilaka-masa-depan-ri-celaka",
            "source": "CNN Indonesia",
            "title": "Rezim UU Omnibus Cilaka Masa Depan RI Celaka"
        },
        {
            "link": "https://www.cnnindonesia.com/nasional/20200921091242-33-548773/pak-jokowi-mohon-terbitkan-perppu-pilkada-demi-jutaan-nyawa",
            "source": "CNN Indonesia",
            "title": "Pak Jokowi Mohon Terbitkan Perppu Pilkada Demi Jutaan Nyawa"
        },
        {
            "link": "https://www.cnbcindonesia.com/market/20201021143910-19-196026/akuisisi-adira-zurich-insurance-siap-jadi-asuransi-syariah",
            "source": "CNN Indonesia",
            "title": " Akuisisi Adira Zurich Insurance Siap Jadi Asuransi Syariah"
        },
        {
            "link": "https://www.cnbcindonesia.com/news/20201021144301-4-196028/demo-mah-lewat-thailand-resmi-buka-pintu-turis-china",
            "source": "CNN Indonesia",
            "title": " Demo Mah Lewat Thailand Resmi Buka Pintu Turis China "
        },
        {
            "link": "https://www.cnbcindonesia.com/tech/20201021143728-37-196024/dipakai-2022-ini-tahapan-pengembangan-vaksin-merah-putih",
            "source": "CNN Indonesia",
            "title": " Dipakai 2022 Ini Tahapan Pengembangan Vaksin Merah Putih"
        },
        {
            "link": "https://finance.detik.com/foto-bisnis/d-5222548/melihat-limbah-kayu-jadi-furnitur-keren",
            "source": "CNN Indonesia",
            "title": "Melihat Limbah Kayu Jadi Furnitur Keren"
        },
        {
            "link": "https://news.detik.com/foto-news/d-5222540/semangat-siswa-sd-belajar-daring-di-tengah-banjir-rob",
            "source": "CNN Indonesia",
            "title": "Semangat Siswa SD Belajar Daring di Tengah Banjir Rob"
        },
        {
            "link": "https://news.detik.com/berita/d-5222539/seluruh-komisi-dprd-rapat-di-resort-puncak-milik-pemda-dki-800-orang-hadir",
            "source": "CNN Indonesia",
            "title": "Seluruh Komisi DPRD Rapat di Resort Puncak Milik Pemda DKI 800 Orang Hadir"
        }
    ],
    "words": {
        "": 1,
        "10": 2,
        "104": 1,
        "107": 1,
        "11": 2,
        "12-60": 1,
        "2": 5,
        "20": 5,
        "2021": 3,
        "2022": 1,
        "2024": 1,
        "21": 1,
        "2536": 1,
        "254": 4,
        "3": 1,
        "4": 1,
        "40": 1,
        "5": 2,
        "53": 1,
        "600": 1,
        "7": 1,
        "8": 3,
        "800": 1,
        "9": 2,
        "ABG": 1,
        "ABK": 1,
        "ARMY": 1,
        "ASN": 6,
        "Ada": 11,
        "Adira": 1,
        "Airlangga": 1,
        "Ajak": 2,
        "Ajukan": 2,
        "Akan": 2,
        "Akhyar": 4,
        "Aksi": 5,
        "Aktif": 2,
        "Akuisisi": 1,
        "Amien": 2,
        "Amin": 2,
        "Anak": 6,
        "Anggota": 1,
        "Angka": 1,
        "Anjing": 1,
        "Antariksa": 2,
        "Aparat": 2,
        "Apartemen": 1,
        "Arab": 1,
        "Asal": 1,
        "Aspri": 2,
        "Asteroid": 2,
        "Asuransi": 1,
        "Asyiknya": 1,
        "Atletico": 1,
        "Australia": 1,
        "Awas": 1,
        "Ayah": 1,
        "Ayam": 1,
        "BLT": 1,
        "BMKG": 2,
        "BPPTKG": 1,
        "BTS": 1,
        "Badan": 1,
        "Bagi": 2,
        "Bakal": 3,
        "Balik": 1,
        "Band": 1,
        "Bandingkan": 1,
        "Banjir": 2,
        "Bank": 2,
        "Banpres": 2,
        "Bantah": 5,
        "Banyak": 2,
        "Barcelona": 1,
        "Baru": 1,
        "Batam": 1,
        "Batu": 2,
        "Bayern": 1,
        "Beda": 1,
        "Begini": 1,
        "Belajar": 1,
        "Benar": 1,
        "Bennu": 2,
        "Bensin": 2,
        "Beredar": 1,
        "Berencana": 1,
        "Bergaya": 1,
        "Berisik": 1,
        "Berlangsung": 1,
        "Beroperasi": 2,
        "Bersyukur": 1,
        "Bertambah": 1,
        "Beruang": 1,
        "Beruntun": 1,
        "Berusia": 1,
        "Besar": 2,
        "Big": 1,
        "Binatang": 1,
        "Bioskop": 8,
        "Bisa": 10,
        "Bocorannya": 1,
        "Bola": 1,
        "Boleh": 1,
        "Bos": 2,
        "Brasil": 1,
        "Buah": 1,
        "Buat": 6,
        "Buatan": 1,
        "Bui": 1,
        "Buka": 7,
        "Buku": 1,
        "Bulan": 2,
        "Bumiputera": 1,
        "Buntut": 1,
        "Bursa": 1,
        "Buruh": 1,
        "Bus": 1,
        "COVID-19": 2,
        "Cafe": 1,
        "Cair": 1,
        "Calon": 1,
        "Capres": 1,
        "Cara": 1,
        "Catatan": 1,
        "Cawalkot": 6,
        "Cek": 2,
        "Ceker": 1,
        "Celaka": 16,
        "China": 3,
        "Cianjur": 1,
        "Cicil": 1,
        "Cilaka": 16,
        "Corona": 20,
        "Covid": 4,
        "Covid-19": 22,
        "DKI": 6,
        "DPR": 1,
        "DPRD": 5,
        "Dana": 1,
        "Daring": 1,
        "Darmawan": 1,
        "Data": 1,
        "Debat": 1,
        "Demi": 18,
        "Demo": 23,
        "Demokrat": 6,
        "Depan": 18,
        "Depok": 1,
        "Desa": 1,
        "Desain": 1,
        "Di": 1,
        "Diabadikan": 1,
        "Dibanding": 2,
        "Diduga": 6,
        "Digeruduk": 1,
        "Digoyang": 1,
        "Dijadwalkan": 2,
        "Dijual": 1,
        "Dikeroyok": 1,
        "Diklaim": 1,
        "Dimanfaatkan": 1,
        "Dipakai": 1,
        "Direksi": 1,
        "Diri": 2,
        "Dirut": 1,
        "Disabilitas": 1,
        "Disebut": 1,
        "Diskriminasi": 1,
        "Disuntik": 1,
        "Dorong": 1,
        "Dorothy": 1,
        "Drama": 1,
        "Dugaan": 2,
        "Duh": 1,
        "Dukung": 4,
        "Dukungan": 1,
        "Dunia": 2,
        "Duta": 1,
        "ECB": 1,
        "Eks": 1,
        "Eksepsi": 2,
        "Elite": 1,
        "Emisi": 1,
        "Eropa": 1,
        "Euro": 1,
        "Flu": 1,
        "Fold": 1,
        "Fredrich": 1,
        "Furnitur": 1,
        "GRATIS": 16,
        "Gaji": 1,
        "Galaxy": 1,
        "Gantung": 1,
        "Gatot": 2,
        "Gelar": 6,
        "Gelombang": 2,
        "Golkar": 2,
        "Gong": 1,
        "Gratin": 1,
        "Gunung": 1,
        "Guru": 4,
        "Habibie": 1,
        "Hadapi": 2,
        "Hadir": 2,
        "Hakim": 2,
        "Hal": 2,
        "Halangi": 3,
        "Hanya": 1,
        "Harga": 2,
        "Hari": 11,
        "Hartarto": 1,
        "Harus": 1,
        "Hasil": 1,
        "Hati-hati": 1,
        "Hendak": 1,
        "Himpun": 2,
        "Hingga": 1,
        "Hopping": 1,
        "Hotel": 1,
        "Hybrid": 1,
        "II": 1,
        "INKA": 1,
        "Identitas": 1,
        "Ikan": 2,
        "Indonesia": 16,
        "Industri": 2,
        "Ingatkan": 1,
        "Ingin": 4,
        "Ini": 23,
        "Insurance": 1,
        "Intan": 2,
        "Intel": 3,
        "Intensitas": 1,
        "Investasi": 1,
        "Iri": 1,
        "Irigasi": 1,
        "Itu-itu": 1,
        "Izin": 1,
        "Jadetabek": 1,
        "Jadi": 18,
        "Jago": 1,
        "Jakarta": 8,
        "Jaksa": 2,
        "Jaktim-Depok": 1,
        "Jalan": 1,
        "Jalur": 1,
        "Jam": 1,
        "Jambi": 3,
        "Jatim": 2,
        "Jaya": 2,
        "Jepang": 3,
        "Jimin": 1,
        "Jiwa": 2,
        "Jokowi": 19,
        "Jokowi-Maruf": 1,
        "Jumlah": 1,
        "Junaidi": 1,
        "Juta": 7,
        "Jutaan": 16,
        "KPK": 2,
        "KSPI": 4,
        "Kader": 1,
        "Kades": 1,
        "Kami": 2,
        "Kampanye": 6,
        "Kandidat": 1,
        "Kantongi": 1,
        "Kartu": 2,
        "Kasus": 4,
        "Kayu": 1,
        "Kece": 1,
        "Kegempaan": 1,
        "Kejaksaan": 1,
        "Keluar": 3,
        "Kembali": 2,
        "Kenaikan": 1,
        "Kepatuhan": 1,
        "Kepemimpinan": 2,
        "Keren": 1,
        "Kerja": 1,
        "Kesehatan": 1,
        "Keterlibatan": 2,
        "Ketika": 1,
        "Keuangan": 1,
        "Keukeuh": 1,
        "Khabib": 4,
        "Khawatir": 1,
        "Khianati": 1,
        "Kilat": 1,
        "Kisah": 3,
        "Kita": 2,
        "Klaim": 3,
        "Kobe": 16,
        "Kocak": 1,
        "Komisi": 1,
        "Kompas": 16,
        "Kontrak": 1,
        "Korea": 2,
        "Korsel": 2,
        "Kosong": 1,
        "Kota": 2,
        "Kumpulkan": 2,
        "Kunjungan": 2,
        "Kurs": 1,
        "La": 1,
        "Laporan": 2,
        "Laporkan": 5,
        "Layak": 1,
        "Lebih": 3,
        "Legenda": 1,
        "Lewandowski": 1,
        "Lewat": 2,
        "Liar": 1,
        "Libatkan": 6,
        "Limbah": 1,
        "Listrik": 1,
        "Live": 1,
        "Lokasi": 2,
        "Lombok": 1,
        "MD": 2,
        "Mah": 1,
        "Mahasiswa": 5,
        "Mahfud": 4,
        "Makan": 1,
        "Makassar": 1,
        "Malah": 2,
        "Man": 1,
        "Mandiri": 1,
        "Manfaat": 1,
        "Manohara": 1,
        "Mantu": 4,
        "Markas": 1,
        "Maruf": 2,
        "Masa": 16,
        "Masakan": 1,
        "Masih": 1,
        "Masjid": 4,
        "Massa": 5,
        "Masuk": 3,
        "Masyarakat": 5,
        "Mau": 2,
        "Mawar": 1,
        "Mayjen": 1,
        "McGregor": 2,
        "McKinsey": 1,
        "Meksiko": 1,
        "Melantai": 1,
        "Melesat": 1,
        "Melihat": 1,
        "Melonjak": 1,
        "Membaik": 1,
        "Menang": 1,
        "Mendapat": 1,
        "Mendiang": 16,
        "Mengcovidkan": 1,
        "Meninggal": 1,
        "Meningkat": 1,
        "Menkes": 1,
        "Menkeu": 1,
        "Menko": 1,
        "Menpora": 1,
        "Menyamar": 5,
        "Menyusup": 5,
        "Merah": 1,
        "Merapi": 1,
        "Merasa": 1,
        "Meski": 1,
        "Messi": 1,
        "Miliar": 1,
        "Milik": 1,
        "Minta": 4,
        "Misi": 2,
        "Misterius": 1,
        "Mobil": 4,
        "Model": 1,
        "Mohon": 16,
        "Motor": 1,
        "Mulyani": 3,
        "Murid": 1,
        "NASA": 2,
        "Naik": 4,
        "Nama": 1,
        "Nasabah": 1,
        "Nasional": 1,
        "Nawaf": 1,
        "Nego": 2,
        "Nikahi": 1,
        "Nikel": 1,
        "Nina": 1,
        "November": 1,
        "Nurani": 1,
        "Nurmantyo": 2,
        "Nyaman": 1,
        "Nyatakan": 1,
        "Nyawa": 16,
        "Offroad": 1,
        "Oknum": 2,
        "Omnibus": 20,
        "Online": 1,
        "Optimalkan": 1,
        "Orang": 5,
        "PCR": 1,
        "PDIP": 1,
        "PEN": 1,
        "PK": 1,
        "PKS": 1,
        "PM": 3,
        "PMK": 1,
        "PP": 1,
        "PSG": 1,
        "PTN": 1,
        "Pada": 1,
        "Pahala": 2,
        "Paham": 16,
        "Pak": 19,
        "Palembang": 1,
        "Pangeran": 1,
        "Panggang": 1,
        "Pangkat": 1,
        "Parkir": 2,
        "Pasar": 1,
        "Pasien": 2,
        "Pele": 1,
        "Pemberian": 1,
        "Pembukaan": 1,
        "Pembuktian": 1,
        "Pembunuhan": 1,
        "Pemda": 1,
        "Pemenggal": 1,
        "Pemprov": 2,
        "Pemuda": 1,
        "Penanganan": 1,
        "Pendaftaran": 2,
        "Pendeta": 2,
        "Pendidik": 1,
        "Penembakan": 2,
        "Penerbangan": 2,
        "Penerima": 2,
        "Pengadilan": 1,
        "Pengembangan": 1,
        "Pengemis": 1,
        "Penghalang": 1,
        "Pengusaha": 1,
        "Penipuan": 1,
        "Penonton": 1,
        "Penularan": 1,
        "Penyintas": 1,
        "Perancis": 1,
        "Peras": 1,
        "Perempuan": 3,
        "Pernikahan": 2,
        "Perpanjang": 1,
        "Perppu": 16,
        "Persebarannya": 1,
        "Persen": 1,
        "Perumahan": 1,
        "Perusahaan": 1,
        "Perwira": 3,
        "Pesan": 1,
        "Pesantren-Madrasah": 1,
        "Pesawat": 2,
        "Petani": 1,
        "Pidana": 1,
        "Pilihannya": 1,
        "Pilkada": 20,
        "Pinangki": 4,
        "Pintu": 3,
        "Pique": 1,
        "Pohon": 1,
        "Polisi": 18,
        "Politik": 1,
        "Polrestabes": 1,
        "Polri": 7,
        "Populer": 1,
        "Positif": 1,
        "Prabowo": 3,
        "Prakerja": 2,
        "Prancis": 4,
        "Presiden": 16,
        "Prihatin": 1,
        "Prioritas": 1,
        "Produksi": 1,
        "Program": 1,
        "Protokol": 1,
        "Pukul": 3,
        "Puluhan": 1,
        "Puncak": 5,
        "Punya": 3,
        "Putih": 1,
        "Q3": 1,
        "RI": 22,
        "RS": 1,
        "RUPSLB": 1,
        "Rais": 2,
        "Rapat": 5,
        "Resep": 1,
        "Resmi": 1,
        "Resort": 1,
        "Rezim": 16,
        "Ribu": 1,
        "Risiko": 1,
        "Rob": 2,
        "Rp": 7,
        "Rp2": 1,
        "Rp238": 1,
        "Rumah": 12,
        "Rusia": 1,
        "Rute": 2,
        "SBY": 1,
        "SD": 1,
        "SMK": 1,
        "Saat": 18,
        "Sabhara": 3,
        "Saja": 1,
        "Salahsatu": 1,
        "Samsung": 1,
        "Sandera": 1,
        "Sapa": 1,
        "Satgas": 4,
        "Satpol": 1,
        "Saud": 1,
        "Saudi": 1,
        "Selesaikan": 1,
        "Seluruh": 1,
        "Semakin": 16,
        "Semangat": 1,
        "Sempat": 2,
        "Semua": 1,
        "Senen": 1,
        "Sentil": 2,
        "Seorang": 1,
        "Sepak": 1,
        "Serentak": 16,
        "Setahun": 1,
        "Sewa": 1,
        "Siap": 1,
        "Siap-siap": 1,
        "Siapkan": 1,
        "Siaran": 1,
        "Simulasi": 1,
        "Sinopsis": 3,
        "Sisa": 1,
        "Siswa": 1,
        "Solidaritas": 1,
        "Sopir": 1,
        "Spesifikasi": 1,
        "Sri": 3,
        "Staycation": 1,
        "Stinky": 2,
        "Studi": 1,
        "Stunting": 1,
        "Suara": 2,
        "Suarez": 1,
        "Subsidi": 1,
        "Sudah": 1,
        "Sulsel": 1,
        "Sumut": 4,
        "Surat": 18,
        "Susunan": 1,
        "Syariah": 2,
        "T": 3,
        "TGPF": 2,
        "Tabungan": 1,
        "Tahap": 1,
        "Tahapan": 1,
        "Tahun": 22,
        "Tak": 22,
        "Taksi": 1,
        "Tambah": 1,
        "Tangsel": 1,
        "Tapi": 1,
        "Tayang": 2,
        "Tembus": 1,
        "Tempat": 1,
        "Temuan": 1,
        "Tengah": 1,
        "Tengkorak": 1,
        "Terancam": 1,
        "Terapkan": 1,
        "Terbanyak": 3,
        "Terbitkan": 16,
        "Terhormat": 16,
        "Terima": 1,
        "Terlaris": 1,
        "Terlibat": 1,
        "Terpanjang": 2,
        "Tersangka": 6,
        "Tertukar": 1,
        "Tes": 1,
        "Tewas": 2,
        "Thailand": 1,
        "Tidak": 4,
        "Tiga": 1,
        "Tim": 4,
        "Tinggi": 1,
        "Titik": 1,
        "Tok": 1,
        "Tolak": 2,
        "Tolong": 1,
        "Tuding": 1,
        "Tukar": 1,
        "Tulis": 1,
        "Tunda": 16,
        "Tunggu": 1,
        "Tuntut": 3,
        "Turis": 1,
        "UEA": 1,
        "UFC": 4,
        "UMKM": 2,
        "UU": 19,
        "Uang": 1,
        "Udang": 1,
        "United": 1,
        "Untuk": 1,
        "Upah": 3,
        "Usai": 2,
        "Usia": 2,
        "V": 1,
        "VIDEO": 20,
        "VIU": 1,
        "Vaksin": 1,
        "Vaksinasi": 1,
        "Vale": 1,
        "Video": 15,
        "Viral": 5,
        "Virus": 2,
        "Wagub": 4,
        "Wakaf": 2,
        "Warga": 1,
        "Wilayah": 1,
        "Wisata": 1,
        "Wow": 1,
        "XXI": 2,
        "Yeremia": 2,
        "Yoo": 1,
        "Yunadi": 1,
        "Z": 1,
        "Zaman": 1,
        "Zona": 1,
        "Zurich": 1,
        "ala": 1,
        "atas": 1,
        "bin": 1,
        "dalam": 1,
        "dan": 1,
        "dari": 1,
        "dengan": 1,
        "di": 1,
        "ePaper": 1,
        "karena": 1,
        "meski": 1,
        "untuk": 1,
        "vs": 1,
        "yang": 1
    }
}